AUTHORS.rst
CONTRIBUTING.rst
LICENSE
MANIFEST.in
README.md
setup.py
docs/Makefile
docs/make.bat
docs/examples/README.rst
docs/source/changelog.rst
docs/source/conf.py
docs/source/index.rst
docs/source/installation.rst
docs/source/min_versions.rst
docs/source/tutorials0/average.rst
docs/source/tutorials0/calibration.rst
docs/source/tutorials0/index.rst
docs/source/tutorials0/integration.rst
docs/source/tutorials0/transformation.rst
docs/source/tutorials1/configuration.rst
docs/source/tutorials1/index.rst
docs/source/tutorials1/replay_analysis.rst
docs/source/tutorials1/run_server.rst
docs/source/tutorials1/test.rst
docs/source/tutorials1/xpd_server.rst
docs/source/tutorials1/xpdsave_server.rst
docs/source/tutorials1/xpdvis_server.rst
docs/source/tutorials1/zmq_proxy.rst
pdfstream/__init__.py
pdfstream/cli.py
pdfstream/data.py
pdfstream/errors.py
pdfstream/io.py
pdfstream/main.py
pdfstream/units.py
pdfstream.egg-info/PKG-INFO
pdfstream.egg-info/SOURCES.txt
pdfstream.egg-info/dependency_links.txt
pdfstream.egg-info/entry_points.txt
pdfstream.egg-info/requires.txt
pdfstream.egg-info/top_level.txt
pdfstream/callbacks/__init__.py
pdfstream/callbacks/analysispipeline.py
pdfstream/callbacks/analyzer.py
pdfstream/callbacks/ananlysisserver.py
pdfstream/callbacks/config.py
pdfstream/callbacks/csvserializer.py
pdfstream/callbacks/darksubtraction.py
pdfstream/callbacks/datakeys.py
pdfstream/callbacks/filenamerender.py
pdfstream/callbacks/imageplotter.py
pdfstream/callbacks/numpyserializer.py
pdfstream/callbacks/plotterbase.py
pdfstream/callbacks/scatterplotter.py
pdfstream/callbacks/serializationpipeline.py
pdfstream/callbacks/serializationserver.py
pdfstream/callbacks/serializerbase.py
pdfstream/callbacks/tiffserilaizer.py
pdfstream/callbacks/visualizationpipeline.py
pdfstream/callbacks/visualizationserver.py
pdfstream/callbacks/waterfallplotter.py
pdfstream/callbacks/yamlserializer.py
pdfstream/data/Ni_dspacing.txt
pdfstream/integration/__init__.py
pdfstream/integration/main.py
pdfstream/integration/tools.py
pdfstream/transformation/__init__.py
pdfstream/transformation/cli.py
pdfstream/transformation/io.py
pdfstream/transformation/main.py
pdfstream/transformation/tools.py
