Metadata-Version: 2.1
Name: pdfstream
Version: 0.6.3
Summary: The configs analysis toolbox for the study on pair distribution function (PDF).
Home-page: https://github.com/xpdAcq/pdfstream
Author: Songsheng Tao
Author-email: st3107@columbia.edu
License: BSD (3-clause)
Classifier: Development Status :: 2 - Pre-Alpha
Classifier: Natural Language :: English
Classifier: Programming Language :: Python :: 3
Requires-Python: >=3.7
License-File: LICENSE
License-File: AUTHORS.rst
Requires-Dist: bluesky
Requires-Dist: databroker
Requires-Dist: fire
Requires-Dist: frozendict
Requires-Dist: numba
Requires-Dist: pyfai
Requires-Dist: pyopencl
Requires-Dist: scikit-beam
Requires-Dist: xpdview
Requires-Dist: xray-vision
